cdlclient/__init__.py
cdlclient/baseproxy.py
cdlclient/config.py
cdlclient/qthelpers.py
cdlclient/remote.py
cdlclient/simplemodel.py
cdlclient/locale/fr/LC_MESSAGES/cdlclient.mo
cdlclient/tests/__init__.py
cdlclient/tests/connect_dialog.py
cdlclient/tests/get_object_dialog.py
cdlclient/tests/imagefile_to_code.py
cdlclient/tests/remoteclient_app.py
cdlclient/tests/remoteclient_base.py
cdlclient/tests/remoteclient_unit.py
cdlclient/widgets/__init__.py
cdlclient/widgets/connection.py
cdlclient/widgets/datalab_banner.py
cdlclient/widgets/objectdialog.py
cdlclient/widgets/svg_icons.py
cdlclient-0.11.0.dist-info/licenses/LICENSE
cdlclient-0.11.0.dist-info/METADATA
cdlclient-0.11.0.dist-info/WHEEL
cdlclient-0.11.0.dist-info/entry_points.txt
cdlclient-0.11.0.dist-info/top_level.txt
cdlclient-0.11.0.dist-info/RECORD
